LICENSE.txt
MANIFEST.in
README.md
setup.cfg
setup.py
arpabetandipaconvertor/__init__.py
arpabetandipaconvertor/arpabet2phoneticalphabet.py
arpabetandipaconvertor/excepts.py
arpabetandipaconvertor/phoneticarphabet2arpabet.py
arpabetandipaconvertor.egg-info/PKG-INFO
arpabetandipaconvertor.egg-info/SOURCES.txt
arpabetandipaconvertor.egg-info/dependency_links.txt
arpabetandipaconvertor.egg-info/top_level.txt
arpabetandipaconvertor/model/__init__.py
arpabetandipaconvertor/model/phoneme.py
arpabetandipaconvertor/model/stress.py
arpabetandipaconvertor/model/syllable.py
arpabetandipaconvertor/model/word.py
test/test_arpabet_2_ipa.py
test/test_ipa_2_arpabet.py