Metadata-Version: 1.1
Name: arpabetandipaconvertor
Version: 1.0.1
Summary: ARPAbet和ipa之间互相转换的工具
Home-page: https://github.com/chdzq/ARPAbetAndIPAConvertor.git
Author: zhanqgi
Author-email: zhangqi.248@gmail.com
License: MIT License
Keywords: IPA ARPAbet ipa arpabet convert ARPAbetAndIPAConvertor
Platform: UNKNOWN
Classifier: Development Status :: 3 - Alpha
Classifier: Intended Audience :: Developers
Classifier: Topic :: Software Development :: Build Tools
Classifier: License :: OSI Approved :: MIT License
Classifier: Programming Language :: Python :: 2
Classifier: Programming Language :: Python :: 2.7
Classifier: Programming Language :: Python :: 3
Classifier: Programming Language :: Python :: 3.3
Classifier: Programming Language :: Python :: 3.4
Classifier: Programming Language :: Python :: 3.5
Classifier: Programming Language :: Python :: 3.6
